{
  "assignment": {
    "name": "dummy",
    "title": "Build a small web app that visualizes city air-quality data",
    "description": "Build a single-page web application that fetches public air-quality measurements for a chosen city and presents them visually. The app should let a user pick a city, see current AQI, and view a 7-day trend.",
    "constraints": [
      "Must be a single-page web app (no multi-page navigation).",
      "Must use a free public air-quality data source.",
      "Must run locally with a single command (no paid hosting required).",
      "Source code under 1500 lines total.",
      "Must include at least one chart/visualization."
    ],
    "deadline_days": 7.0
  },
  "config": {
    "n_rooms": 2,
    "max_depth": 3,
    "max_options": 3
  },
  "metrics": {
    "wall_time_s": 35.61053013801575,
    "total_calls": 40,
    "by_role": {
      "option_generator": {
        "n": 13,
        "input_tokens": 4792,
        "output_tokens": 1009,
        "duration_s": 16.127729892730713
      },
      "consultant": {
        "n": 27,
        "input_tokens": 9224,
        "output_tokens": 4130,
        "duration_s": 63.17293858528137
      }
    },
    "total_input_tokens": 14016,
    "total_output_tokens": 5139
  },
  "recommended_plan": [
    "Open-AQ platform (no authentication required)",
    "Vue 3 (simple CDN or build setup)",
    "Chart.js with vue-chartjs wrapper"
  ],
  "root": {
    "history": [],
    "decision": "Data source selection",
    "is_leaf": false,
    "verdict": {
      "quality": 0.7518518518518518,
      "est_days": 4.722222222222222,
      "notes": "Solid, well-scoped plan with proven tools and realistic scope. Main risk: Open-AQ's API response times and data availability vary by region\u2014test city selection early. Consider pre-selecting 2-3 reliable cities if API proves inconsistent.",
      "n_consultations": 27
    },
    "chosen_best_option": "Open-AQ platform (no authentication required)",
    "branches": [
      {
        "option": "OpenWeatherMap Air Pollution API (free tier with API key)",
        "child": {
          "history": [
            "OpenWeatherMap Air Pollution API (free tier with API key)"
          ],
          "decision": "Frontend framework choice",
          "is_leaf": false,
          "verdict": {
            "quality": 0.7522222222222221,
            "est_days": 4.833333333333333,
            "notes": "Plan is solid and well-scoped: OpenWeatherMap free tier provides reliable historical data, React+Vite is efficient for SPAs, and Chart.js is proven for this use case. Main risks are API rate limits (requires careful caching) and ensuring 7-day historical data is accessible on the free tier\u2014verify API docs early to confirm historical endpoints are available without paid upgrade.",
            "n_consultations": 9
          },
          "chosen_best_option": "React with Vite",
          "branches": [
            {
              "option": "Vanilla JavaScript (HTML/CSS/JS only)",
              "child": {
                "history": [
                  "OpenWeatherMap Air Pollution API (free tier with API key)",
                  "Vanilla JavaScript (HTML/CSS/JS only)"
                ],
                "decision": "Chart library choice",
                "is_leaf": false,
                "verdict": {
                  "quality": 0.73,
                  "est_days": 4.833333333333333,
                  "notes": "Plan is solid and well-scoped for the constraints. OpenWeatherMap's free tier supports current AQI + historical data needed for 7-day trends, Chart.js is proven lightweight choice, and vanilla JS keeps complexity low. Main risk: OpenWeatherMap's historical data availability on free tier may require fallback to synthetic trend data or switching to WAQI API\u2014verify data source depth before committing 2+ days to implementation.",
                  "n_consultations": 3
                },
                "chosen_best_option": "Chart.js (lightweight, well-documented, ~40KB)",
                "branches": [
                  {
                    "option": "Chart.js (lightweight, well-documented, ~40KB)",
                    "child": {
                      "history": [
                        "OpenWeatherMap Air Pollution API (free tier with API key)",
                        "Vanilla JavaScript (HTML/CSS/JS only)",
                        "Chart.js (lightweight, well-documented, ~40KB)"
                      ],
                      "decision": null,
                      "is_leaf": true,
                      "verdict": {
                        "quality": 0.82,
                        "est_days": 3.5,
                        "notes": "Plan is solid and well-scoped for the constraints. OpenWeatherMap's free tier supports current AQI + historical data needed for 7-day trends, Chart.js is proven lightweight choice, and vanilla JS keeps complexity low. Main risk: OpenWeatherMap's historical data availability on free tier may require fallback to synthetic trend data or switching to WAQI API\u2014verify data source depth before committing 2+ days to implementation.",
                        "n_consultations": 1
                      },
                      "chosen_best_option": null,
                      "branches": []
                    }
                  },
                  {
                    "option": "D3.js (powerful but steeper learning curve, larger)",
                    "child": {
                      "history": [
                        "OpenWeatherMap Air Pollution API (free tier with API key)",
                        "Vanilla JavaScript (HTML/CSS/JS only)",
                        "D3.js (powerful but steeper learning curve, larger)"
                      ],
                      "decision": null,
                      "is_leaf": true,
                      "verdict": {
                        "quality": 0.65,
                        "est_days": 5.5,
                        "notes": "The plan is feasible but has a critical risk: D3.js introduces significant overhead for a simple 7-day trend chart, likely consuming 200+ lines just for basic setup and pushing toward the 1500-line limit. Consider swapping D3.js for Chart.js or a lightweight alternative (Plotly.js, ApexCharts) to preserve code budget and reduce learning friction, while still meeting all requirements comfortably.",
                        "n_consultations": 1
                      },
                      "chosen_best_option": null,
                      "branches": []
                    }
                  },
                  {
                    "option": "Inline SVG/Canvas (no dependency, more code to write)",
                    "child": {
                      "history": [
                        "OpenWeatherMap Air Pollution API (free tier with API key)",
                        "Vanilla JavaScript (HTML/CSS/JS only)",
                        "Inline SVG/Canvas (no dependency, more code to write)"
                      ],
                      "decision": null,
                      "is_leaf": true,
                      "verdict": {
                        "quality": 0.72,
                        "est_days": 5.5,
                        "notes": "The plan is feasible and meets all constraints, but rolling custom SVG/Canvas visualization will consume ~20% of effort and risk visual polish issues under time pressure. Consider Chart.js (lightweight, single file) as a pragmatic middle ground that preserves the no-build-step advantage while freeing time for data handling and UX refinement.",
                        "n_consultations": 1
                      },
                      "chosen_best_option": null,
                      "branches": []
                    }
                  }
                ]
              }
            },
            {
              "option": "React with Vite",
              "child": {
                "history": [
                  "OpenWeatherMap Air Pollution API (free tier with API key)",
                  "React with Vite"
                ],
                "decision": "Chart library for visualization",
                "is_leaf": false,
                "verdict": {
                  "quality": 0.7633333333333333,
                  "est_days": 4.833333333333333,
                  "notes": "Plan is solid and well-scoped: OpenWeatherMap free tier provides reliable historical data, React+Vite is efficient for SPAs, and Chart.js is proven for this use case. Main risks are API rate limits (requires careful caching) and ensuring 7-day historical data is accessible on the free tier\u2014verify API docs early to confirm historical endpoints are available without paid upgrade.",
                  "n_consultations": 3
                },
                "chosen_best_option": "Chart.js with react-chartjs-2 (lightweight, familiar)",
                "branches": [
                  {
                    "option": "Chart.js with react-chartjs-2 (lightweight, familiar)",
                    "child": {
                      "history": [
                        "OpenWeatherMap Air Pollution API (free tier with API key)",
                        "React with Vite",
                        "Chart.js with react-chartjs-2 (lightweight, familiar)"
                      ],
                      "decision": null,
                      "is_leaf": true,
                      "verdict": {
                        "quality": 0.82,
                        "est_days": 4.5,
                        "notes": "Plan is solid and well-scoped: OpenWeatherMap free tier provides reliable historical data, React+Vite is efficient for SPAs, and Chart.js is proven for this use case. Main risks are API rate limits (requires careful caching) and ensuring 7-day historical data is accessible on the free tier\u2014verify API docs early to confirm historical endpoints are available without paid upgrade.",
                        "n_consultations": 1
                      },
                      "chosen_best_option": null,
                      "branches": []
                    }
                  },
                  {
                    "option": "Recharts (React-native, declarative)",
                    "child": {
                      "history": [
                        "OpenWeatherMap Air Pollution API (free tier with API key)",
                        "React with Vite",
                        "Recharts (React-native, declarative)"
                      ],
                      "decision": null,
                      "is_leaf": true,
                      "verdict": {
                        "quality": 0.75,
                        "est_days": 4.5,
                        "notes": "Solid tech choices with proven libraries, but OpenWeatherMap's free tier has rate limits and may require careful API key management. Plan should explicitly address: (1) fallback/mock data strategy if API calls fail, (2) local storage for caching 7-day history since the API doesn't inherently provide historical data\u2014this is the highest risk, requiring daily snapshots or a workaround, and (3) whether Recharts is truly 'React-native' (it's a React charting library, which is fine, just verify no native dependencies complicate local setup).",
                        "n_consultations": 1
                      },
                      "chosen_best_option": null,
                      "branches": []
                    }
                  },
                  {
                    "option": "Plotly.js (feature-rich but heavier)",
                    "child": {
                      "history": [
                        "OpenWeatherMap Air Pollution API (free tier with API key)",
                        "React with Vite",
                        "Plotly.js (feature-rich but heavier)"
                      ],
                      "decision": null,
                      "is_leaf": true,
                      "verdict": {
                        "quality": 0.72,
                        "est_days": 5.5,
                        "notes": "The tech stack is solid and well-matched to constraints, but Plotly.js adds unnecessary weight for a simple 7-day trend chart\u2014consider Chart.js or Recharts instead to keep bundle size down and stay comfortably under 1500 lines. API integration and React/Vite setup are straightforward; main risk is handling API rate limits and missing cities gracefully.",
                        "n_consultations": 1
                      },
                      "chosen_best_option": null,
                      "branches": []
                    }
                  }
                ]
              }
            },
            {
              "option": "Vue 3 with simple build setup",
              "child": {
                "history": [
                  "OpenWeatherMap Air Pollution API (free tier with API key)",
                  "Vue 3 with simple build setup"
                ],
                "decision": "Charting library for visualization",
                "is_leaf": false,
                "verdict": {
                  "quality": 0.7633333333333333,
                  "est_days": 4.833333333333333,
                  "notes": "Solid tech choices that align well with constraints\u2014OpenWeatherMap free tier supports air-quality queries, Vue 3 + Chart.js keeps complexity low and code concise. Main risk: free API rate limits (60 calls/min) and data freshness; verify the free tier actually returns 7-day historical data rather than just current readings, as this may require a different API or synthetic trend generation.",
                  "n_consultations": 3
                },
                "chosen_best_option": "Chart.js (lightweight, well-documented, minimal dependencies)",
                "branches": [
                  {
                    "option": "Chart.js (lightweight, well-documented, minimal dependencies)",
                    "child": {
                      "history": [
                        "OpenWeatherMap Air Pollution API (free tier with API key)",
                        "Vue 3 with simple build setup",
                        "Chart.js (lightweight, well-documented, minimal dependencies)"
                      ],
                      "decision": null,
                      "is_leaf": true,
                      "verdict": {
                        "quality": 0.82,
                        "est_days": 4.5,
                        "notes": "Solid tech choices that align well with constraints\u2014OpenWeatherMap free tier supports air-quality queries, Vue 3 + Chart.js keeps complexity low and code concise. Main risk: free API rate limits (60 calls/min) and data freshness; verify the free tier actually returns 7-day historical data rather than just current readings, as this may require a different API or synthetic trend generation.",
                        "n_consultations": 1
                      },
                      "chosen_best_option": null,
                      "branches": []
                    }
                  },
                  {
                    "option": "Plotly.js (more features but larger bundle)",
                    "child": {
                      "history": [
                        "OpenWeatherMap Air Pollution API (free tier with API key)",
                        "Vue 3 with simple build setup",
                        "Plotly.js (more features but larger bundle)"
                      ],
                      "decision": null,
                      "is_leaf": true,
                      "verdict": {
                        "quality": 0.72,
                        "est_days": 5.5,
                        "notes": "Plan is solid and achievable, but Plotly.js adds unnecessary bundle bloat for a simple 7-day trend chart\u2014Chart.js or even SVG would be lighter and faster to implement. Verify OpenWeatherMap free tier provides 7-day historical data; if only current AQI is available, the trend feature will require a workaround (polling over time or a different data source).",
                        "n_consultations": 1
                      },
                      "chosen_best_option": null,
                      "branches": []
                    }
                  },
                  {
                    "option": "Plain SVG/Canvas (maximum control, minimal overhead)",
                    "child": {
                      "history": [
                        "OpenWeatherMap Air Pollution API (free tier with API key)",
                        "Vue 3 with simple build setup",
                        "Plain SVG/Canvas (maximum control, minimal overhead)"
                      ],
                      "decision": null,
                      "is_leaf": true,
                      "verdict": {
                        "quality": 0.75,
                        "est_days": 4.5,
                        "notes": "Solid technical choices with realistic scope, but OpenWeatherMap free tier has limited historical data (current + forecast only, not full 7-day history), requiring either a workaround (e.g., polling/caching) or fallback to a different API like IQAir or WAQI. Vue 3 + SVG is appropriate for the constraints and should comfortably fit under 1500 lines with a single-command local dev server (vite).",
                        "n_consultations": 1
                      },
                      "chosen_best_option": null,
                      "branches": []
                    }
                  }
                ]
              }
            }
          ]
        }
      },
      {
        "option": "AirVisual/IQAir API (free tier available)",
        "child": {
          "history": [
            "AirVisual/IQAir API (free tier available)"
          ],
          "decision": "Frontend framework/stack",
          "is_leaf": false,
          "verdict": {
            "quality": 0.7444444444444444,
            "est_days": 4.722222222222222,
            "notes": "The plan is solid and well-scoped\u2014no-build HTML/CSS/JS with Chart.js is appropriate for this assignment. Main risk: IQAir free tier has strict rate limits (10 calls/min, 30/day) and may require API key registration; verify this works with the assignment's \"local, single command\" requirement and consider fallback data or a local mock if the API becomes bottleneck. Otherwise, 4\u20135 days is realistic, leaving comfortable buffer before the 7-day deadline.",
            "n_consultations": 9
          },
          "chosen_best_option": "Plain HTML/CSS/JavaScript (no build step)",
          "branches": [
            {
              "option": "Plain HTML/CSS/JavaScript (no build step)",
              "child": {
                "history": [
                  "AirVisual/IQAir API (free tier available)",
                  "Plain HTML/CSS/JavaScript (no build step)"
                ],
                "decision": "Chart library choice",
                "is_leaf": false,
                "verdict": {
                  "quality": 0.7633333333333333,
                  "est_days": 4.5,
                  "notes": "The plan is solid and well-scoped\u2014no-build HTML/CSS/JS with Chart.js is appropriate for this assignment. Main risk: IQAir free tier has strict rate limits (10 calls/min, 30/day) and may require API key registration; verify this works with the assignment's \"local, single command\" requirement and consider fallback data or a local mock if the API becomes bottleneck. Otherwise, 4\u20135 days is realistic, leaving comfortable buffer before the 7-day deadline.",
                  "n_consultations": 3
                },
                "chosen_best_option": "Chart.js (lightweight, easy setup, good for time-series)",
                "branches": [
                  {
                    "option": "Chart.js (lightweight, easy setup, good for time-series)",
                    "child": {
                      "history": [
                        "AirVisual/IQAir API (free tier available)",
                        "Plain HTML/CSS/JavaScript (no build step)",
                        "Chart.js (lightweight, easy setup, good for time-series)"
                      ],
                      "decision": null,
                      "is_leaf": true,
                      "verdict": {
                        "quality": 0.82,
                        "est_days": 4.5,
                        "notes": "The plan is solid and well-scoped\u2014no-build HTML/CSS/JS with Chart.js is appropriate for this assignment. Main risk: IQAir free tier has strict rate limits (10 calls/min, 30/day) and may require API key registration; verify this works with the assignment's \"local, single command\" requirement and consider fallback data or a local mock if the API becomes bottleneck. Otherwise, 4\u20135 days is realistic, leaving comfortable buffer before the 7-day deadline.",
                        "n_consultations": 1
                      },
                      "chosen_best_option": null,
                      "branches": []
                    }
                  },
                  {
                    "option": "Plotly.js (more interactive, larger bundle)",
                    "child": {
                      "history": [
                        "AirVisual/IQAir API (free tier available)",
                        "Plain HTML/CSS/JavaScript (no build step)",
                        "Plotly.js (more interactive, larger bundle)"
                      ],
                      "decision": null,
                      "is_leaf": true,
                      "verdict": {
                        "quality": 0.75,
                        "est_days": 3.5,
                        "notes": "The plan is straightforward and feasible, but verify IQAir free tier rate limits and data freshness before starting\u2014some free tiers have restrictive quotas. Plotly.js adds ~3MB to bundle and may complicate local development; consider Chart.js or Lightweight alternatives if load time becomes an issue.",
                        "n_consultations": 1
                      },
                      "chosen_best_option": null,
                      "branches": []
                    }
                  },
                  {
                    "option": "SVG/Canvas manual rendering (smallest footprint, more code)",
                    "child": {
                      "history": [
                        "AirVisual/IQAir API (free tier available)",
                        "Plain HTML/CSS/JavaScript (no build step)",
                        "SVG/Canvas manual rendering (smallest footprint, more code)"
                      ],
                      "decision": null,
                      "is_leaf": true,
                      "verdict": {
                        "quality": 0.72,
                        "est_days": 5.5,
                        "notes": "Plan is feasible and meets all constraints, but manual SVG/Canvas rendering will consume significant effort (~30-40% of timeline) for marginal benefit\u2014consider Chart.js or Plotly.js (lightweight CDN libraries) instead to reduce complexity and risk missing the line-count budget. Verify IQAir free tier includes 7-day historical data before committing; some tiers only offer current readings.",
                        "n_consultations": 1
                      },
                      "chosen_best_option": null,
                      "branches": []
                    }
                  }
                ]
              }
            },
            {
              "option": "React with Vite or Create React App",
              "child": {
                "history": [
                  "AirVisual/IQAir API (free tier available)",
                  "React with Vite or Create React App"
                ],
                "decision": "Charting library for visualization",
                "is_leaf": false,
                "verdict": {
                  "quality": 0.7166666666666667,
                  "est_days": 4.833333333333333,
                  "notes": "Solid tech stack choice with proven libraries, but IQAir free tier has strict rate limits (10 calls/min, 30/day) which may frustrate testing; consider OpenWeatherMap or fallback to mock data for development. Vite is better than CRA for staying under 1500 lines\u2014plan aggressive component reuse and avoid unnecessary abstraction layers.",
                  "n_consultations": 3
                },
                "chosen_best_option": "Chart.js with react-chartjs-2 (lightweight, familiar)",
                "branches": [
                  {
                    "option": "Chart.js with react-chartjs-2 (lightweight, familiar)",
                    "child": {
                      "history": [
                        "AirVisual/IQAir API (free tier available)",
                        "React with Vite or Create React App",
                        "Chart.js with react-chartjs-2 (lightweight, familiar)"
                      ],
                      "decision": null,
                      "is_leaf": true,
                      "verdict": {
                        "quality": 0.75,
                        "est_days": 4.5,
                        "notes": "Solid tech stack choice with proven libraries, but IQAir free tier has strict rate limits (10 calls/min, 30/day) which may frustrate testing; consider OpenWeatherMap or fallback to mock data for development. Vite is better than CRA for staying under 1500 lines\u2014plan aggressive component reuse and avoid unnecessary abstraction layers.",
                        "n_consultations": 1
                      },
                      "chosen_best_option": null,
                      "branches": []
                    }
                  },
                  {
                    "option": "Recharts (React-native, minimal setup)",
                    "child": {
                      "history": [
                        "AirVisual/IQAir API (free tier available)",
                        "React with Vite or Create React App",
                        "Recharts (React-native, minimal setup)"
                      ],
                      "decision": null,
                      "is_leaf": true,
                      "verdict": {
                        "quality": 0.75,
                        "est_days": 4.5,
                        "notes": "Plan is solid and well-scoped: AirVisual free tier supports current AQI + historical data, React+Vite minimizes setup friction, and Recharts handles visualization elegantly within constraints. Main risks: AirVisual free tier has rate limits (10 calls/min) and may require API key signup validation; verify it returns 7-day historical data before committing (some free tiers only show current conditions).",
                        "n_consultations": 1
                      },
                      "chosen_best_option": null,
                      "branches": []
                    }
                  },
                  {
                    "option": "D3.js (powerful but steeper learning curve, risks exceeding line limit)",
                    "child": {
                      "history": [
                        "AirVisual/IQAir API (free tier available)",
                        "React with Vite or Create React App",
                        "D3.js (powerful but steeper learning curve, risks exceeding line limit)"
                      ],
                      "decision": null,
                      "is_leaf": true,
                      "verdict": {
                        "quality": 0.65,
                        "est_days": 5.5,
                        "notes": "D3.js introduces unnecessary complexity and significantly risks the 1500-line constraint; substitute with Chart.js or Recharts for faster implementation. Verify IQAir free tier includes 7-day historical data (it may not)\u2014confirm this immediately as it's a critical dependency.",
                        "n_consultations": 1
                      },
                      "chosen_best_option": null,
                      "branches": []
                    }
                  }
                ]
              }
            },
            {
              "option": "Vue.js with simple setup",
              "child": {
                "history": [
                  "AirVisual/IQAir API (free tier available)",
                  "Vue.js with simple setup"
                ],
                "decision": "Chart library for 7-day trend visualization",
                "is_leaf": false,
                "verdict": {
                  "quality": 0.7533333333333333,
                  "est_days": 4.833333333333333,
                  "notes": "Solid technology choices with proven free APIs and lightweight frameworks. Primary risk: IQAir's free tier has strict rate limits (10 calls/month) and may require API key approval\u2014verify access immediately and consider a fallback source (OpenWeatherMap, WAQI) to avoid blocking progress. Plan includes good margin within the 7-day deadline.",
                  "n_consultations": 3
                },
                "chosen_best_option": "Chart.js with vue-chartjs wrapper",
                "branches": [
                  {
                    "option": "Chart.js with vue-chartjs wrapper",
                    "child": {
                      "history": [
                        "AirVisual/IQAir API (free tier available)",
                        "Vue.js with simple setup",
                        "Chart.js with vue-chartjs wrapper"
                      ],
                      "decision": null,
                      "is_leaf": true,
                      "verdict": {
                        "quality": 0.82,
                        "est_days": 4.5,
                        "notes": "Solid technology choices with proven free APIs and lightweight frameworks. Primary risk: IQAir's free tier has strict rate limits (10 calls/month) and may require API key approval\u2014verify access immediately and consider a fallback source (OpenWeatherMap, WAQI) to avoid blocking progress. Plan includes good margin within the 7-day deadline.",
                        "n_consultations": 1
                      },
                      "chosen_best_option": null,
                      "branches": []
                    }
                  },
                  {
                    "option": "Simple SVG/Canvas with vanilla JavaScript",
                    "child": {
                      "history": [
                        "AirVisual/IQAir API (free tier available)",
                        "Vue.js with simple setup",
                        "Simple SVG/Canvas with vanilla JavaScript"
                      ],
                      "decision": null,
                      "is_leaf": true,
                      "verdict": {
                        "quality": 0.72,
                        "est_days": 5.5,
                        "notes": "Plan is feasible but has a critical risk: IQAir's free tier has strict rate limits (10 calls/min) and may require API key approval. Recommend validating API access immediately and having a fallback (e.g., Open-Meteo's air-quality endpoints or mock data) ready. Vue.js + vanilla visualization is solid for scope, but mixing Vue with direct DOM manipulation (canvas/SVG) can create maintenance friction\u2014consider a lightweight charting library (Chart.js, Recharts) instead to stay under 1500 lines cleanly.",
                        "n_consultations": 1
                      },
                      "chosen_best_option": null,
                      "branches": []
                    }
                  },
                  {
                    "option": "Lightweight alternative like Lightweight Charts or Plotly.js",
                    "child": {
                      "history": [
                        "AirVisual/IQAir API (free tier available)",
                        "Vue.js with simple setup",
                        "Lightweight alternative like Lightweight Charts or Plotly.js"
                      ],
                      "decision": null,
                      "is_leaf": true,
                      "verdict": {
                        "quality": 0.72,
                        "est_days": 4.5,
                        "notes": "Plan is feasible but has one critical risk: IQAir's free tier has strict rate limits (10 calls/min, 30/day) and may not reliably serve 7-day historical data\u2014verify API response structure early. Vue.js + Lightweight Charts is a solid, size-conscious stack that should easily fit the 1500-line constraint; local execution is straightforward with a simple dev server.",
                        "n_consultations": 1
                      },
                      "chosen_best_option": null,
                      "branches": []
                    }
                  }
                ]
              }
            }
          ]
        }
      },
      {
        "option": "Open-AQ platform (no authentication required)",
        "child": {
          "history": [
            "Open-AQ platform (no authentication required)"
          ],
          "decision": "Frontend framework choice",
          "is_leaf": false,
          "verdict": {
            "quality": 0.758888888888889,
            "est_days": 4.611111111111111,
            "notes": "Solid, well-scoped plan with proven tools and realistic scope. Main risk: Open-AQ's API response times and data availability vary by region\u2014test city selection early. Consider pre-selecting 2-3 reliable cities if API proves inconsistent.",
            "n_consultations": 9
          },
          "chosen_best_option": "Vue 3 (simple CDN or build setup)",
          "branches": [
            {
              "option": "React (with hooks, create-react-app or Vite)",
              "child": {
                "history": [
                  "Open-AQ platform (no authentication required)",
                  "React (with hooks, create-react-app or Vite)"
                ],
                "decision": "Charting library choice",
                "is_leaf": false,
                "verdict": {
                  "quality": 0.7733333333333333,
                  "est_days": 4.5,
                  "notes": "Solid technical choices with good library maturity and documentation. Main risk: Open-AQ API has rate limits and inconsistent historical data availability per city\u2014verify upfront that your target cities have 7-day trend data, and implement fallback/caching strategy to avoid hitting limits during development and testing.",
                  "n_consultations": 3
                },
                "chosen_best_option": "Chart.js with react-chartjs-2 (familiar API, good docs)",
                "branches": [
                  {
                    "option": "Recharts (React-native, minimal setup)",
                    "child": {
                      "history": [
                        "Open-AQ platform (no authentication required)",
                        "React (with hooks, create-react-app or Vite)",
                        "Recharts (React-native, minimal setup)"
                      ],
                      "decision": null,
                      "is_leaf": true,
                      "verdict": {
                        "quality": 0.75,
                        "est_days": 4.5,
                        "notes": "Solid tech choices\u2014Open-AQ is reliable and free, React/Vite is appropriate, and Recharts integrates well. However, the plan lacks detail on data fetching strategy (Open-AQ has rate limits and coordinate-based queries), error handling, and how the city picker will work\u2014clarify whether you'll use a hardcoded city list or reverse-geocoding API to avoid scope creep.",
                        "n_consultations": 1
                      },
                      "chosen_best_option": null,
                      "branches": []
                    }
                  },
                  {
                    "option": "Chart.js with react-chartjs-2 (familiar API, good docs)",
                    "child": {
                      "history": [
                        "Open-AQ platform (no authentication required)",
                        "React (with hooks, create-react-app or Vite)",
                        "Chart.js with react-chartjs-2 (familiar API, good docs)"
                      ],
                      "decision": null,
                      "is_leaf": true,
                      "verdict": {
                        "quality": 0.82,
                        "est_days": 4.5,
                        "notes": "Solid technical choices with good library maturity and documentation. Main risk: Open-AQ API has rate limits and inconsistent historical data availability per city\u2014verify upfront that your target cities have 7-day trend data, and implement fallback/caching strategy to avoid hitting limits during development and testing.",
                        "n_consultations": 1
                      },
                      "chosen_best_option": null,
                      "branches": []
                    }
                  },
                  {
                    "option": "Plain SVG/Canvas (full control, more code)",
                    "child": {
                      "history": [
                        "Open-AQ platform (no authentication required)",
                        "React (with hooks, create-react-app or Vite)",
                        "Plain SVG/Canvas (full control, more code)"
                      ],
                      "decision": null,
                      "is_leaf": true,
                      "verdict": {
                        "quality": 0.75,
                        "est_days": 4.5,
                        "notes": "The plan is solid and technically feasible\u2014Open-AQ is reliable, React is appropriate for a SPA, and SVG/Canvas gives good control. However, building custom charts from scratch with SVG/Canvas will consume significant development time and token budget; consider a lightweight charting library (Recharts, Chart.js) to stay under 1500 lines and reduce risk of missing the 7-day visualization deadline.",
                        "n_consultations": 1
                      },
                      "chosen_best_option": null,
                      "branches": []
                    }
                  }
                ]
              }
            },
            {
              "option": "Vue 3 (simple CDN or build setup)",
              "child": {
                "history": [
                  "Open-AQ platform (no authentication required)",
                  "Vue 3 (simple CDN or build setup)"
                ],
                "decision": "Chart/visualization library",
                "is_leaf": false,
                "verdict": {
                  "quality": 0.7966666666666665,
                  "est_days": 4.5,
                  "notes": "Solid, well-scoped plan with proven tools and realistic scope. Main risk: Open-AQ's API response times and data availability vary by region\u2014test city selection early. Consider pre-selecting 2-3 reliable cities if API proves inconsistent.",
                  "n_consultations": 3
                },
                "chosen_best_option": "Chart.js with vue-chartjs wrapper",
                "branches": [
                  {
                    "option": "Chart.js with vue-chartjs wrapper",
                    "child": {
                      "history": [
                        "Open-AQ platform (no authentication required)",
                        "Vue 3 (simple CDN or build setup)",
                        "Chart.js with vue-chartjs wrapper"
                      ],
                      "decision": null,
                      "is_leaf": true,
                      "verdict": {
                        "quality": 0.82,
                        "est_days": 4.5,
                        "notes": "Solid, well-scoped plan with proven tools and realistic scope. Main risk: Open-AQ's API response times and data availability vary by region\u2014test city selection early. Consider pre-selecting 2-3 reliable cities if API proves inconsistent.",
                        "n_consultations": 1
                      },
                      "chosen_best_option": null,
                      "branches": []
                    }
                  },
                  {
                    "option": "Plotly.js (standalone, no wrapper needed)",
                    "child": {
                      "history": [
                        "Open-AQ platform (no authentication required)",
                        "Vue 3 (simple CDN or build setup)",
                        "Plotly.js (standalone, no wrapper needed)"
                      ],
                      "decision": null,
                      "is_leaf": true,
                      "verdict": {
                        "quality": 0.82,
                        "est_days": 4.5,
                        "notes": "Open-AQ + Vue 3 + Plotly.js is a solid, well-matched tech stack that satisfies all constraints. Main risk: Open-AQ's API can have rate-limiting and inconsistent historical data availability across cities\u2014recommend testing data completeness early and having a fallback city/mock data for demo purposes.",
                        "n_consultations": 1
                      },
                      "chosen_best_option": null,
                      "branches": []
                    }
                  },
                  {
                    "option": "Simple SVG/Canvas with native DOM manipulation",
                    "child": {
                      "history": [
                        "Open-AQ platform (no authentication required)",
                        "Vue 3 (simple CDN or build setup)",
                        "Simple SVG/Canvas with native DOM manipulation"
                      ],
                      "decision": null,
                      "is_leaf": true,
                      "verdict": {
                        "quality": 0.75,
                        "est_days": 4.5,
                        "notes": "Solid choices overall\u2014Open-AQ is reliable and Vue 3 handles SPA requirements well. Main risk: SVG/Canvas visualization could become tedious without a charting library (Chart.js or similar); consider adding it to the plan to stay well under the 1500-line limit while delivering polished output. Timeline is comfortable given the 7-day deadline.",
                        "n_consultations": 1
                      },
                      "chosen_best_option": null,
                      "branches": []
                    }
                  }
                ]
              }
            },
            {
              "option": "Vanilla JavaScript (no framework)",
              "child": {
                "history": [
                  "Open-AQ platform (no authentication required)",
                  "Vanilla JavaScript (no framework)"
                ],
                "decision": "Charting library choice",
                "is_leaf": false,
                "verdict": {
                  "quality": 0.7066666666666667,
                  "est_days": 4.833333333333333,
                  "notes": "Solid tech choices that align well with constraints: Open-AQ is reliable and free, vanilla JS keeps dependencies minimal, and Chart.js is lightweight via CDN. Main risks are Open-AQ API rate limits (mitigate with caching) and handling missing data for some cities\u2014plan for fallback messaging and test with 3-4 cities early.",
                  "n_consultations": 3
                },
                "chosen_best_option": "Chart.js (lightweight, CDN-based, minimal setup)",
                "branches": [
                  {
                    "option": "Chart.js (lightweight, CDN-based, minimal setup)",
                    "child": {
                      "history": [
                        "Open-AQ platform (no authentication required)",
                        "Vanilla JavaScript (no framework)",
                        "Chart.js (lightweight, CDN-based, minimal setup)"
                      ],
                      "decision": null,
                      "is_leaf": true,
                      "verdict": {
                        "quality": 0.82,
                        "est_days": 3.5,
                        "notes": "Solid tech choices that align well with constraints: Open-AQ is reliable and free, vanilla JS keeps dependencies minimal, and Chart.js is lightweight via CDN. Main risks are Open-AQ API rate limits (mitigate with caching) and handling missing data for some cities\u2014plan for fallback messaging and test with 3-4 cities early.",
                        "n_consultations": 1
                      },
                      "chosen_best_option": null,
                      "branches": []
                    }
                  },
                  {
                    "option": "D3.js (powerful but steeper learning curve, larger footprint)",
                    "child": {
                      "history": [
                        "Open-AQ platform (no authentication required)",
                        "Vanilla JavaScript (no framework)",
                        "D3.js (powerful but steeper learning curve, larger footprint)"
                      ],
                      "decision": null,
                      "is_leaf": true,
                      "verdict": {
                        "quality": 0.65,
                        "est_days": 5.5,
                        "notes": "D3.js is overkill for a simple 7-day trend chart and will consume ~200-300 lines just for setup/learning, leaving less room for polish. Consider Chart.js or even native Canvas instead\u2014it's 80% as capable with 20% of the complexity, better fitting the 1500-line constraint and giving buffer for error handling, city search UX, and data fetching robustness.",
                        "n_consultations": 1
                      },
                      "chosen_best_option": null,
                      "branches": []
                    }
                  },
                  {
                    "option": "Plain HTML5 Canvas (most control, most code required)",
                    "child": {
                      "history": [
                        "Open-AQ platform (no authentication required)",
                        "Vanilla JavaScript (no framework)",
                        "Plain HTML5 Canvas (most control, most code required)"
                      ],
                      "decision": null,
                      "is_leaf": true,
                      "verdict": {
                        "quality": 0.65,
                        "est_days": 5.5,
                        "notes": "The plan is feasible and meets all constraints, but Canvas for charting is a time-intensive choice that risks hitting the 1500-line limit or cutting corners on polish. Consider a lightweight charting library (Chart.js ~30KB) to reclaim dev time for better data handling, error states, and city search UX\u2014vanilla Canvas can consume 200-300 lines just for axis rendering and tooltips.",
                        "n_consultations": 1
                      },
                      "chosen_best_option": null,
                      "branches": []
                    }
                  }
                ]
              }
            }
          ]
        }
      }
    ]
  },
  "llm_calls": [
    {
      "agent_role": "option_generator",
      "model": "claude-haiku-4-5-20251001",
      "input_tokens": 348,
      "output_tokens": 79,
      "duration_s": 1.306868076324463,
      "started_at": 1776815753.180537,
      "history_depth": 0,
      "ok": true,
      "error": null
    },
    {
      "agent_role": "option_generator",
      "model": "claude-haiku-4-5-20251001",
      "input_tokens": 362,
      "output_tokens": 65,
      "duration_s": 1.003018856048584,
      "started_at": 1776815754.4877892,
      "history_depth": 1,
      "ok": true,
      "error": null
    },
    {
      "agent_role": "option_generator",
      "model": "claude-haiku-4-5-20251001",
      "input_tokens": 357,
      "output_tokens": 73,
      "duration_s": 1.1110191345214844,
      "started_at": 1776815754.4894788,
      "history_depth": 1,
      "ok": true,
      "error": null
    },
    {
      "agent_role": "option_generator",
      "model": "claude-haiku-4-5-20251001",
      "input_tokens": 362,
      "output_tokens": 68,
      "duration_s": 1.514251947402954,
      "started_at": 1776815754.488905,
      "history_depth": 1,
      "ok": true,
      "error": null
    },
    {
      "agent_role": "option_generator",
      "model": "claude-haiku-4-5-20251001",
      "input_tokens": 374,
      "output_tokens": 79,
      "duration_s": 1.1229448318481445,
      "started_at": 1776815755.49317,
      "history_depth": 2,
      "ok": true,
      "error": null
    },
    {
      "agent_role": "option_generator",
      "model": "claude-haiku-4-5-20251001",
      "input_tokens": 377,
      "output_tokens": 82,
      "duration_s": 1.15789794921875,
      "started_at": 1776815755.491068,
      "history_depth": 2,
      "ok": true,
      "error": null
    },
    {
      "agent_role": "option_generator",
      "model": "claude-haiku-4-5-20251001",
      "input_tokens": 371,
      "output_tokens": 80,
      "duration_s": 1.168673038482666,
      "started_at": 1776815755.492398,
      "history_depth": 2,
      "ok": true,
      "error": null
    },
    {
      "agent_role": "option_generator",
      "model": "claude-haiku-4-5-20251001",
      "input_tokens": 373,
      "output_tokens": 72,
      "duration_s": 1.1019370555877686,
      "started_at": 1776815755.603117,
      "history_depth": 2,
      "ok": true,
      "error": null
    },
    {
      "agent_role": "option_generator",
      "model": "claude-haiku-4-5-20251001",
      "input_tokens": 368,
      "output_tokens": 84,
      "duration_s": 1.2188928127288818,
      "started_at": 1776815755.603897,
      "history_depth": 2,
      "ok": true,
      "error": null
    },
    {
      "agent_role": "option_generator",
      "model": "claude-haiku-4-5-20251001",
      "input_tokens": 376,
      "output_tokens": 82,
      "duration_s": 1.2602808475494385,
      "started_at": 1776815755.600781,
      "history_depth": 2,
      "ok": true,
      "error": null
    },
    {
      "agent_role": "option_generator",
      "model": "claude-haiku-4-5-20251001",
      "input_tokens": 377,
      "output_tokens": 80,
      "duration_s": 1.1516962051391602,
      "started_at": 1776815756.0034828,
      "history_depth": 2,
      "ok": true,
      "error": null
    },
    {
      "agent_role": "option_generator",
      "model": "claude-haiku-4-5-20251001",
      "input_tokens": 375,
      "output_tokens": 87,
      "duration_s": 1.273569107055664,
      "started_at": 1776815756.004964,
      "history_depth": 2,
      "ok": true,
      "error": null
    },
    {
      "agent_role": "option_generator",
      "model": "claude-haiku-4-5-20251001",
      "input_tokens": 372,
      "output_tokens": 78,
      "duration_s": 1.736680030822754,
      "started_at": 1776815756.005839,
      "history_depth": 2,
      "ok": true,
      "error": null
    },
    {
      "agent_role": "consultant",
      "model": "claude-haiku-4-5-20251001",
      "input_tokens": 341,
      "output_tokens": 127,
      "duration_s": 2.047388792037964,
      "started_at": 1776815756.6179042,
      "history_depth": 3,
      "ok": true,
      "error": null
    },
    {
      "agent_role": "consultant",
      "model": "claude-haiku-4-5-20251001",
      "input_tokens": 342,
      "output_tokens": 126,
      "duration_s": 2.077255964279175,
      "started_at": 1776815756.616441,
      "history_depth": 3,
      "ok": true,
      "error": null
    },
    {
      "agent_role": "consultant",
      "model": "claude-haiku-4-5-20251001",
      "input_tokens": 346,
      "output_tokens": 133,
      "duration_s": 1.9467360973358154,
      "started_at": 1776815758.693844,
      "history_depth": 3,
      "ok": true,
      "error": null
    },
    {
      "agent_role": "consultant",
      "model": "claude-haiku-4-5-20251001",
      "input_tokens": 346,
      "output_tokens": 133,
      "duration_s": 1.8567180633544922,
      "started_at": 1776815760.640787,
      "history_depth": 3,
      "ok": true,
      "error": null
    },
    {
      "agent_role": "consultant",
      "model": "claude-haiku-4-5-20251001",
      "input_tokens": 341,
      "output_tokens": 379,
      "duration_s": 5.034765958786011,
      "started_at": 1776815758.6656,
      "history_depth": 3,
      "ok": true,
      "error": null
    },
    {
      "agent_role": "consultant",
      "model": "claude-haiku-4-5-20251001",
      "input_tokens": 347,
      "output_tokens": 112,
      "duration_s": 2.001823902130127,
      "started_at": 1776815762.497809,
      "history_depth": 3,
      "ok": true,
      "error": null
    },
    {
      "agent_role": "consultant",
      "model": "claude-haiku-4-5-20251001",
      "input_tokens": 342,
      "output_tokens": 122,
      "duration_s": 2.0096800327301025,
      "started_at": 1776815763.700592,
      "history_depth": 3,
      "ok": true,
      "error": null
    },
    {
      "agent_role": "consultant",
      "model": "claude-haiku-4-5-20251001",
      "input_tokens": 337,
      "output_tokens": 165,
      "duration_s": 2.6659369468688965,
      "started_at": 1776815764.499907,
      "history_depth": 3,
      "ok": true,
      "error": null
    },
    {
      "agent_role": "consultant",
      "model": "claude-haiku-4-5-20251001",
      "input_tokens": 339,
      "output_tokens": 122,
      "duration_s": 1.8636717796325684,
      "started_at": 1776815765.710531,
      "history_depth": 3,
      "ok": true,
      "error": null
    },
    {
      "agent_role": "consultant",
      "model": "claude-haiku-4-5-20251001",
      "input_tokens": 340,
      "output_tokens": 111,
      "duration_s": 1.7387909889221191,
      "started_at": 1776815767.574471,
      "history_depth": 3,
      "ok": true,
      "error": null
    },
    {
      "agent_role": "consultant",
      "model": "claude-haiku-4-5-20251001",
      "input_tokens": 337,
      "output_tokens": 119,
      "duration_s": 1.8457491397857666,
      "started_at": 1776815769.3135219,
      "history_depth": 3,
      "ok": true,
      "error": null
    },
    {
      "agent_role": "consultant",
      "model": "claude-haiku-4-5-20251001",
      "input_tokens": 337,
      "output_tokens": 373,
      "duration_s": 5.017261028289795,
      "started_at": 1776815767.1661,
      "history_depth": 3,
      "ok": true,
      "error": null
    },
    {
      "agent_role": "consultant",
      "model": "claude-haiku-4-5-20251001",
      "input_tokens": 337,
      "output_tokens": 116,
      "duration_s": 1.6969683170318604,
      "started_at": 1776815771.1595469,
      "history_depth": 3,
      "ok": true,
      "error": null
    },
    {
      "agent_role": "consultant",
      "model": "claude-haiku-4-5-20251001",
      "input_tokens": 336,
      "output_tokens": 127,
      "duration_s": 2.2877109050750732,
      "started_at": 1776815772.856819,
      "history_depth": 3,
      "ok": true,
      "error": null
    },
    {
      "agent_role": "consultant",
      "model": "claude-haiku-4-5-20251001",
      "input_tokens": 339,
      "output_tokens": 354,
      "duration_s": 4.920958042144775,
      "started_at": 1776815772.183619,
      "history_depth": 3,
      "ok": true,
      "error": null
    },
    {
      "agent_role": "consultant",
      "model": "claude-haiku-4-5-20251001",
      "input_tokens": 342,
      "output_tokens": 129,
      "duration_s": 2.1591038703918457,
      "started_at": 1776815775.1447911,
      "history_depth": 3,
      "ok": true,
      "error": null
    },
    {
      "agent_role": "consultant",
      "model": "claude-haiku-4-5-20251001",
      "input_tokens": 349,
      "output_tokens": 103,
      "duration_s": 1.7328789234161377,
      "started_at": 1776815777.104836,
      "history_depth": 3,
      "ok": true,
      "error": null
    },
    {
      "agent_role": "consultant",
      "model": "claude-haiku-4-5-20251001",
      "input_tokens": 343,
      "output_tokens": 129,
      "duration_s": 1.9437587261199951,
      "started_at": 1776815777.3041651,
      "history_depth": 3,
      "ok": true,
      "error": null
    },
    {
      "agent_role": "consultant",
      "model": "claude-haiku-4-5-20251001",
      "input_tokens": 344,
      "output_tokens": 108,
      "duration_s": 1.7369639873504639,
      "started_at": 1776815779.248179,
      "history_depth": 3,
      "ok": true,
      "error": null
    },
    {
      "agent_role": "consultant",
      "model": "claude-haiku-4-5-20251001",
      "input_tokens": 347,
      "output_tokens": 152,
      "duration_s": 2.85780930519104,
      "started_at": 1776815778.837983,
      "history_depth": 3,
      "ok": true,
      "error": null
    },
    {
      "agent_role": "consultant",
      "model": "claude-haiku-4-5-20251001",
      "input_tokens": 346,
      "output_tokens": 128,
      "duration_s": 2.1542749404907227,
      "started_at": 1776815780.985418,
      "history_depth": 3,
      "ok": true,
      "error": null
    },
    {
      "agent_role": "consultant",
      "model": "claude-haiku-4-5-20251001",
      "input_tokens": 346,
      "output_tokens": 120,
      "duration_s": 1.6455070972442627,
      "started_at": 1776815781.6960158,
      "history_depth": 3,
      "ok": true,
      "error": null
    },
    {
      "agent_role": "consultant",
      "model": "claude-haiku-4-5-20251001",
      "input_tokens": 348,
      "output_tokens": 101,
      "duration_s": 1.6388819217681885,
      "started_at": 1776815783.341755,
      "history_depth": 3,
      "ok": true,
      "error": null
    },
    {
      "agent_role": "consultant",
      "model": "claude-haiku-4-5-20251001",
      "input_tokens": 341,
      "output_tokens": 134,
      "duration_s": 2.0648789405822754,
      "started_at": 1776815783.139982,
      "history_depth": 3,
      "ok": true,
      "error": null
    },
    {
      "agent_role": "consultant",
      "model": "claude-haiku-4-5-20251001",
      "input_tokens": 336,
      "output_tokens": 115,
      "duration_s": 1.8349220752716064,
      "started_at": 1776815784.980897,
      "history_depth": 3,
      "ok": true,
      "error": null
    },
    {
      "agent_role": "consultant",
      "model": "claude-haiku-4-5-20251001",
      "input_tokens": 335,
      "output_tokens": 163,
      "duration_s": 2.4379749298095703,
      "started_at": 1776815785.205065,
      "history_depth": 3,
      "ok": true,
      "error": null
    },
    {
      "agent_role": "consultant",
      "model": "claude-haiku-4-5-20251001",
      "input_tokens": 340,
      "output_tokens": 129,
      "duration_s": 1.9545679092407227,
      "started_at": 1776815786.81609,
      "history_depth": 3,
      "ok": true,
      "error": null
    }
  ],
  "ts_finished": 1776815788.771487
}